apple_calendar_integration/__init__.py
apple_calendar_integration/calendar_api.py
apple_calendar_integration-0.0.1.dist-info/METADATA
apple_calendar_integration-0.0.1.dist-info/RECORD
apple_calendar_integration-0.0.1.dist-info/WHEEL
apple_calendar_integration-0.0.1.dist-info/top_level.txt
