Metadata-Version: 2.1
Name: apple-calendar-integration
Version: 0.0.1
Summary: The ICloud API for events management
Home-page: https://github.com/SoulSoft/apple-calendar-integration
Author: SoulSoft Inc
Author-email: admin@soulsoftinc.com
License: UNKNOWN
Platform: UNKNOWN
Classifier: Programming Language :: Python :: 3
Classifier: License :: OSI Approved :: MIT License
Classifier: Operating System :: OS Independent
